vector_algebra/Vectors.py
vector_algebra-1.0.5.dist-info/LICENSE
vector_algebra-1.0.5.dist-info/METADATA
vector_algebra-1.0.5.dist-info/WHEEL
vector_algebra-1.0.5.dist-info/entry_points.txt
vector_algebra-1.0.5.dist-info/top_level.txt
vector_algebra-1.0.5.dist-info/RECORD
