Metadata-Version: 2.1
Name: vector-algebra
Version: 1.0.5
Summary: It helps in solving vector algebra
Home-page: https://github.com/deepakdashcode/vector.git
Author: Deepak Kumar Dash
Author-email: dipudash.2003@gmail.com
License: MIT
Platform: UNKNOWN
Classifier: License :: OSI Approved :: MIT License
Classifier: Programming Language :: Python :: 3.6
Classifier: Programming Language :: Python :: 3.7
Classifier: Programming Language :: Python :: 3.8
